feedopml.py
feedopml-0.1.dist-info/DESCRIPTION.rst
feedopml-0.1.dist-info/METADATA
feedopml-0.1.dist-info/RECORD
feedopml-0.1.dist-info/WHEEL
feedopml-0.1.dist-info/metadata.json
feedopml-0.1.dist-info/top_level.txt
