Metadata-Version: 2.0
Name: feedopml
Version: 0.1
Summary: UNKNOWN
Home-page: https://github.com/DasIch/feedopml
Author: Daniel Neuhäuser
Author-email: ich@danielneuhaeuser.de
License: UNKNOWN
Platform: UNKNOWN
Requires-Dist: lxml
